fast_html2md/__init__.py
fast_html2md/cleaners.py
fast_html2md/converter.py
fast_html2md/exceptions.py
fast_html2md/models.py
fast_html2md-0.1.3.dist-info/METADATA
fast_html2md-0.1.3.dist-info/WHEEL
fast_html2md-0.1.3.dist-info/licenses/LICENSE
fast_html2md-0.1.3.dist-info/RECORD
